nodeless/__init__.py
nodeless/nodeless.py
nodeless-py/__init__.py
nodeless-py/nodeless.py
nodelesspy/__init__.py
nodelesspy/nodeless.py
nodeless-0.0.1.dist-info/LICENSE
nodeless-0.0.1.dist-info/METADATA
nodeless-0.0.1.dist-info/WHEEL
nodeless-0.0.1.dist-info/top_level.txt
nodeless-0.0.1.dist-info/RECORD
